{
  "node_0 2k kuibysheva": [
    588.5,
    221.0,
    [
      "node_1 2k kuibysheva",
      "node_2 2k kuibysheva",
      "node_3 2k kuibysheva"
    ],
    "2k",
    "kuibysheva"
  ],
  "node_1 2k kuibysheva": [
    729.5,
    221.0,
    [
      "node_0 2k kuibysheva"
    ],
    "2k",
    "kuibysheva"
  ],
  "node_2 2k kuibysheva": [
    588.5,
    279.5,
    [
      "node_0 2k kuibysheva",
      "node_7 2k kuibysheva",
      "node_9 2k kuibysheva"
    ],
    "2k",
    "kuibysheva"
  ],
  "node_3 2k kuibysheva": [
    588.5,
    113.5,
    [
      "node_4 2k kuibysheva",
      "node_0 2k kuibysheva"
    ],
    "2k",
    "kuibysheva"
  ],
  "node_4 2k kuibysheva": [
    859.0,
    113.5,
    [
      "node_3 2k kuibysheva",
      "node_5 2k kuibysheva"
    ],
    "2k",
    "kuibysheva"
  ],
  "node_5 2k kuibysheva": [
    859.0,
    55.0,
    [
      "node_4 2k kuibysheva",
      "node_6 2k kuibysheva"
    ],
    "2k",
    "kuibysheva"
  ],
  "node_6 2k kuibysheva": [
    775.0,
    55.0,
    [
      "node_5 2k kuibysheva"
    ],
    "2k",
    "kuibysheva"
  ],
  "node_7 2k kuibysheva": [
    668.5,
    279.5,
    [
      "node_8 2k kuibysheva",
      "node_2 2k kuibysheva"
    ],
    "2k",
    "kuibysheva"
  ],
  "node_8 2k kuibysheva": [
    668.5,
    371.5,
    [
      "node_7 2k kuibysheva"
    ],
    "2k",
    "kuibysheva"
  ],
  "node_9 2k kuibysheva": [
    464.5,
    279.5,
    [
      "node_13 2k kuibysheva",
      "node_2 2k kuibysheva",
      "node_10 2k kuibysheva"
    ],
    "2k",
    "kuibysheva"
  ],
  "node_10 2k kuibysheva": [
    267.0,
    279.5,
    [
      "node_9 2k kuibysheva",
      "node_12 2k kuibysheva",
      "node_11 2k kuibysheva"
    ],
    "2k",
    "kuibysheva"
  ],
  "node_11 2k kuibysheva": [
    211.0,
    279.5,
    [
      "node_10 2k kuibysheva"
    ],
    "2k",
    "kuibysheva"
  ],
  "node_12 2k kuibysheva": [
    267.0,
    371.5,
    [
      "node_10 2k kuibysheva"
    ],
    "2k",
    "kuibysheva"
  ],
  "node_13 2k kuibysheva": [
    464.5,
    371.5,
    [
      "node_9 2k kuibysheva"
    ],
    "2k",
    "kuibysheva"
  ]
}